srequests/__init__.py
srequests/srequests.py
srequests-0.0.3.dist-info/LICENSE
srequests-0.0.3.dist-info/METADATA
srequests-0.0.3.dist-info/WHEEL
srequests-0.0.3.dist-info/top_level.txt
srequests-0.0.3.dist-info/RECORD
