Metadata-Version: 2.1
Name: srequests
Version: 0.0.3
Summary: A package for taking requests from a Scratch project.
Author-email: 89paradox <68936a@gmail.com>
Project-URL: Homepage, https://github.com/heyimocto/srequests
Project-URL: Bug Tracker, https://github.com/heyimocto/srequests/issues
Classifier: Programming Language :: Python :: 3
Classifier: Operating System :: OS Independent
Requires-Python: >=3.7
License-File: LICENSE
Requires-Dist: scratchattach
